{
  "required": true,
  "package": "meteordevelopment.meteorclient.mixin",
  "compatibilityLevel": "JAVA_17",
  "plugin": "meteordevelopment.meteorclient.MixinPlugin",
  "client": [
    "CapabilityTrackerMixin",
    "minecraft.block.AbstractBlockAccessor",
    "minecraft.block.AbstractBlockMixin",
    "minecraft.block.BlockEntityTypeAccessor",
    "minecraft.block.BlockMixin",
    "minecraft.block.BlockStateMixin",
    "minecraft.block.CactusBlockMixin",
    "minecraft.block.CobwebBlockMixin",
    "minecraft.block.FluidBlockMixin",
    "minecraft.block.PowderSnowBlockMixin",
    "minecraft.block.ShulkerBoxBlockMixin",
    "minecraft.block.SlimeBlockMixin",
    "minecraft.client.KeyboardMixin",
    "minecraft.client.MinecraftClientAccessor",
    "minecraft.client.MinecraftClientMixin",
    "minecraft.client.MouseMixin",
    "minecraft.client.SoundSystemMixin",
    "minecraft.client.SplashTextResourceSupplierMixin",
    "minecraft.client.color.BiomeColorsMixin",
    "minecraft.client.color.FoliageColorsMixin",
    "minecraft.client.font.TextHandlerAccessor",
    "minecraft.client.font.TextVisitFactoryMixin",
    "minecraft.client.gui.hud.BossBarHudMixin",
    "minecraft.client.gui.hud.ChatHudAccessor",
    "minecraft.client.gui.hud.ChatHudMixin",
    "minecraft.client.gui.hud.InGameHudMixin",
    "minecraft.client.gui.hud.InGameOverlayRendererMixin",
    "minecraft.client.gui.hud.PlayerListHudMixin",
    "minecraft.client.gui.screen.ChatScreenMixin",
    "minecraft.client.gui.screen.CommandSuggestorMixin",
    "minecraft.client.gui.screen.ScreenMixin",
    "minecraft.client.gui.screen.TitleScreenMixin",
    "minecraft.client.gui.screen.ingame.AbstractFurnaceScreenMixin",
    "minecraft.client.gui.screen.ingame.BookEditScreenMixin",
    "minecraft.client.gui.screen.ingame.BookScreenMixin",
    "minecraft.client.gui.screen.ingame.BrewingStandScreenMixin",
    "minecraft.client.gui.screen.ingame.CreativeInventoryScreenAccessor",
    "minecraft.client.gui.screen.ingame.CreativeSlotMixin",
    "minecraft.client.gui.screen.ingame.DisconnectedScreenMixin",
    "minecraft.client.gui.screen.ingame.GenericContainerScreenMixin",
    "minecraft.client.gui.screen.ingame.HandledScreenAccessor",
    "minecraft.client.gui.screen.ingame.HandledScreenMixin",
    "minecraft.client.gui.screen.ingame.ShulkerBoxScreenMixin",
    "minecraft.client.gui.screen.ingame.SignEditScreenAccessor",
    "minecraft.client.gui.screen.multiplayer.MultiplayerScreenMixin",
    "minecraft.client.gui.widget.AbstractButtonWidgetAccessor",
    "minecraft.client.input.KeyboardInputMixin",
    "minecraft.client.item.ModelPredicateProviderRegistryMixin",
    "minecraft.client.network.AbstractClientPlayerEntityMixin",
    "minecraft.client.network.ClientPlayNetworkHandlerAccessor",
    "minecraft.client.network.ClientPlayNetworkHandlerMixin",
    "minecraft.client.network.ClientPlayerEntityAccessor",
    "minecraft.client.network.ClientPlayerEntityMixin",
    "minecraft.client.network.ClientPlayerInteractionManagerAccessor",
    "minecraft.client.network.ClientPlayerInteractionManagerMixin",
    "minecraft.client.option.GameOptionsMixin",
    "minecraft.client.option.KeyBindingAccessor",
    "minecraft.client.particle.FireworksSparkParticleMixin",
    "minecraft.client.particle.FireworksSparkParticleSubMixin",
    "minecraft.client.particle.ParticleManagerMixin",
    "minecraft.client.render.BackgroundRendererMixin",
    "minecraft.client.render.BufferBuilderAccessor",
    "minecraft.client.render.BufferRendererAccessor",
    "minecraft.client.render.CameraMixin",
    "minecraft.client.render.GameRendererMixin",
    "minecraft.client.render.MapRendererAccessor",
    "minecraft.client.render.MapRendererMixin",
    "minecraft.client.render.RenderLayersMixin",
    "minecraft.client.render.RenderTickCounterMixin",
    "minecraft.client.render.WorldRendererAccessor",
    "minecraft.client.render.WorldRendererMixin",
    "minecraft.client.render.block.BlockModelRendererMixin",
    "minecraft.client.render.block.BlockRenderManagerMixin",
    "minecraft.client.render.block.FluidRendererMixin",
    "minecraft.client.render.block.entity.BannerBlockEntityRendererMixin",
    "minecraft.client.render.block.entity.BlockEntityRenderDispatcherMixin",
    "minecraft.client.render.block.entity.EnchantingTableBlockEntityRendererMixin",
    "minecraft.client.render.block.entity.MobSpawnerBlockEntityRendererMixin",
    "minecraft.client.render.block.entity.SignBlockEntityRendererMixin",
    "minecraft.client.render.chunk.ChunkOcclusionDataBuilderMixin",
    "minecraft.client.render.entity.EndCrystalEntityRendererMixin",
    "minecraft.client.render.entity.EntityRenderDispatcherMixin",
    "minecraft.client.render.entity.EntityRendererMixin",
    "minecraft.client.render.entity.ItemEntityRendererMixin",
    "minecraft.client.render.entity.LightningEntityRendererMixin",
    "minecraft.client.render.entity.LivingEntityRendererMixin",
    "minecraft.client.render.entity.PlayerEntityRendererMixin",
    "minecraft.client.render.entity.feature.ArmorFeatureRendererMixin",
    "minecraft.client.render.item.HeldItemRendererMixin",
    "minecraft.client.util.DefaultSkinHelperMixin",
    "minecraft.client.world.ClientWorldMixin",
    "minecraft.entity.EntityAccessor",
    "minecraft.entity.EntityMixin",
    "minecraft.entity.ItemEntityMixin",
    "minecraft.entity.LivingEntityAccessor",
    "minecraft.entity.LivingEntityMixin",
    "minecraft.entity.effect.StatusEffectInstanceAccessor",
    "minecraft.entity.effect.StatusEffectInstanceMixin",
    "minecraft.entity.passive.HorseBaseEntityMixin",
    "minecraft.entity.passive.LlamaEntityMixin",
    "minecraft.entity.player.PlayerEntityMixin",
    "minecraft.entity.projectile.FireworkRocketEntityMixin",
    "minecraft.entity.projectile.ProjectileEntityAccessor",
    "minecraft.entity.projectile.ProjectileInGroundAccessor",
    "minecraft.entity.vehicle.BoatEntityMixin",
    "minecraft.item.BlockItemMixin",
    "minecraft.item.CrossbowItemAccessor",
    "minecraft.item.EntityBucketItemAccessor",
    "minecraft.item.ItemMixin",
    "minecraft.item.ItemStackAccessor",
    "minecraft.item.ItemStackMixin",
    "minecraft.item.TridentItemMixin",
    "minecraft.network.ClientConnectionAccessor",
    "minecraft.network.ClientConnectionInitChannelMixin",
    "minecraft.network.ClientConnectionMixin",
    "minecraft.network.packet.c2s.CloseHandledScreenC2SPacketAccessor",
    "minecraft.network.packet.c2s.CustomPayloadC2SPacketAccessor",
    "minecraft.network.packet.c2s.PlayerInteractEntityC2SPacketMixin",
    "minecraft.network.packet.c2s.PlayerMoveC2SPacketAccessor",
    "minecraft.network.packet.c2s.PlayerMoveC2SPacketMixin",
    "minecraft.network.packet.s2c.EntityVelocityUpdateS2CPacketAccessor",
    "minecraft.network.packet.s2c.ExplosionS2CPacketMixin",
    "minecraft.network.packet.s2c.PlayerPositionLookS2CPacketAccessor",
    "minecraft.resource.NamespaceResourceManagerMixin",
    "minecraft.resource.ReloadableResourceManagerImplMixin",
    "minecraft.screen.AbstractFurnaceScreenHandlerAccessor",
    "minecraft.screen.HorseScreenHandlerAccessor",
    "minecraft.screen.slot.SlotMixin",
    "minecraft.server.MinecraftServerAccessor",
    "minecraft.util.IdentifierAccessor",
    "minecraft.util.crash.CrashReportMixin",
    "minecraft.util.hit.BlockHitResultAccessor",
    "minecraft.util.math.BoxMixin",
    "minecraft.util.math.Matrix4fMixin",
    "minecraft.util.math.Vec3dMixin",
    "minecraft.util.registry.RegistryMixin",
    "minecraft.world.RaycastContextMixin",
    "minecraft.world.WorldAccessor",
    "minecraft.world.chunk.ChunkAccessor",
    "minecraft.world.chunk.WorldChunkMixin",
    "minecraft.world.chunk.light.ChunkSkyLightProviderMixin",
    "minecraft.world.dimension.DimensionTypeAccessor",
    "minecraft.world.entity.EntityTrackingSectionAccessor",
    "minecraft.world.entity.SectionedEntityCacheAccessor",
    "minecraft.world.entity.SimpleEntityLookupAccessor",
    "minecraft.world.explosion.ExplosionMixin"
  ],
  "injectors": {
    "defaultRequire": 1
  }
}
